{
  "hdhub4u": "https://new3.hdhub4u.cl/?utm=mn1",
  "moviesdrive": "https://new5.moviesdrives.my",
  "gofile": "https://gofile.io",
  "hubdrive": "https://hubdrive.tips",
  "gdflix": "https://new1.gdflix.app/cgi-sys/defaultwebpage.cgi",
  "gdflix2": "https://new2.gdflix.app/?no=cache",
  "hubcloud": "https://hubcloud.cx",
  "hubcdn": "https://hubcdn.fans/lander",
  "4khdhub": "https://4khdhub.one/",
  "pixeldrain": "https://pixeldrain.dev",
  "multimovies": "https://multimovies.study/",
  "multimoviesshg": "https://multimoviesshg.com"
}
